xara_units/__init__.py
xara_units/__main__.py
xara_units/cgs.py
xara_units/english.py
xara_units/fas.py
xara_units/fks.py
xara_units/fps.py
xara_units/ias.py
xara_units/iks.py
xara_units/ips.py
xara_units/mks.py
xara_units/si.py
xara_units/units.py
xara_units-0.0.0.dist-info/METADATA
xara_units-0.0.0.dist-info/WHEEL
xara_units-0.0.0.dist-info/top_level.txt
xara_units-0.0.0.dist-info/RECORD
